rpc42b2t/__init__.py
rpc42b2t-1.0.0.dist-info/LICENSE
rpc42b2t-1.0.0.dist-info/METADATA
rpc42b2t-1.0.0.dist-info/WHEEL
rpc42b2t-1.0.0.dist-info/entry_points.txt
rpc42b2t-1.0.0.dist-info/top_level.txt
rpc42b2t-1.0.0.dist-info/RECORD
