Metadata-Version: 2.1
Name: rpc42b2t
Version: 1.0.0
Summary: An improved Discord RPC for 2b2t.org
Home-page: https://github.com/korochun/rpc42b2t
Author: korochun
Author-email: korochun@list.ru
License: GPLv3
Keywords: Minecraft RPC Discord
Platform: UNKNOWN
Classifier: Development Status :: 5 - Production/Stable
Classifier: Intended Audience :: End Users/Desktop
Classifier: License :: OSI Approved :: GNU General Public License v3 (GPLv3)
Classifier: Programming Language :: Python :: 3.5
Classifier: Topic :: Communications :: Chat
Classifier: Topic :: Games/Entertainment
Requires-Python: >=3.5
Requires-Dist: pypresence (>=4.0.0)
